bgg4py/__init__.py
bgg4py/api.py
bgg4py/cli.py
bgg4py/request.py
bgg4py/valueobject/__init__.py
bgg4py/valueobject/bgg.py
bgg4py/valueobject/family_items.py
bgg4py/valueobject/forrum_list.py
bgg4py/valueobject/forum.py
bgg4py/valueobject/geeklist.py
bgg4py/valueobject/hot_item.py
bgg4py/valueobject/search.py
bgg4py/valueobject/thing.py
bgg4py/valueobject/thread.py
bgg4py/valueobject/user.py
bgg4py/valueobject/user_collection.py
bgg4py-0.0.2.dist-info/LICENSE
bgg4py-0.0.2.dist-info/WHEEL
bgg4py-0.0.2.dist-info/METADATA
bgg4py-0.0.2.dist-info/RECORD
