Metadata-Version: 2.1
Name: bgg4py
Version: 0.0.2
Summary: 
Home-page: https://github.com/hiroaqii/bgg4py
License: MIT
Author: hiroaqii
Author-email: hiroaqii@gmail.com
Requires-Python: >=3.7,<4.0
Classifier: License :: OSI Approved :: MIT License
Classifier: Programming Language :: Python :: 3
Classifier: Programming Language :: Python :: 3.7
Classifier: Programming Language :: Python :: 3.8
Requires-Dist: click (>=7.1.2,<8.0.0)
Requires-Dist: devtools (>=0.5.1,<0.6.0)
Requires-Dist: pydantic (>=1.5.1,<2.0.0)
Requires-Dist: requests (>=2.23.0,<3.0.0)
Requires-Dist: xmltodict (>=0.12.0,<0.13.0)
Project-URL: Repository, https://github.com/hiroaqii/bgg4py
